mythicalgebra/__init__.py
mythicalgebra/core.py
mythicalgebra-0.1.0.dist-info/licenses/LICENSE
mythicalgebra-0.1.0.dist-info/METADATA
mythicalgebra-0.1.0.dist-info/WHEEL
mythicalgebra-0.1.0.dist-info/top_level.txt
mythicalgebra-0.1.0.dist-info/RECORD
