Metadata-Version: 2.4
Name: mythicalgebra
Version: 0.1.0
Summary: A modular system for modeling myths as structured combinations of narrative elements.
Author-email: Pierre-Louis Suckrow <suckrowpierre@gmail.com>
Requires-Python: >=3.12
License-File: LICENSE
Requires-Dist: numpy>=2.3.2
Dynamic: license-file
